[
  {
    "time": 2023.01,
    "pipeline": "Wharf",
    "activity": "Berthing",
    "eventName": "OnStart",
    "vesselId": "V0002",
    "wharf": "wharf_S",
    "wharfmark_start": 39.85,
    "wharfmark_end": 310.15,
    "LOA": 240.29,
    "discharging": 1221,
    "loading": 763,
    "qcDetails": {
      "18": "DTQC59",
      "19": "DTQC60",
      "20": "DTQC61"
    }
  },
  {
    "time": 2171.6,
    "pipeline": "Wharf",
    "activity": "Berthing",
    "eventName": "OnStart",
    "vesselId": "V0005",
    "wharf": "wharf_N",
    "wharfmark_start": 3487.05,
    "wharfmark_end": 3729.85,
    "LOA": 212.82,
    "discharging": 498,
    "loading": 277,
    "qcDetails": {
      "6": "DTQC07",
      "7": "DTQC08"
    }
  },
  {
    "time": 2313.81,
    "pipeline": "Wharf",
    "activity": "Berthing",
    "eventName": "OnStart",
    "vesselId": "V0001",
    "wharf": "wharf_N",
    "wharfmark_start": 39.85,
    "wharfmark_end": 389.05,
    "LOA": 319.24,
    "discharging": 1288,
    "loading": 549,
    "qcDetails": {
      "24": "DTQC25",
      "25": "DTQC26"
    }
  },
  {
    "time": 2942.56,
    "pipeline": "Wharf",
    "activity": "Berthing",
    "eventName": "OnStart",
    "vesselId": "V0003",
    "wharf": "wharf_S",
    "wharfmark_start": 3544.74,
    "wharfmark_end": 3735.54,
    "LOA": 160.81,
    "discharging": 1056,
    "loading": 1134,
    "qcDetails": {
      "14": "DTQC55",
      "15": "DTQC56",
      "16": "DTQC57",
      "17": "DTQC58"
    }
  },
  {
    "time": 3127.57,
    "pipeline": "Wharf",
    "activity": "Berthing",
    "eventName": "OnStart",
    "vesselId": "V0012",
    "wharf": "wharf_N",
    "wharfmark_start": 3295.11,
    "wharfmark_end": 3445.67,
    "LOA": 63.17,
    "discharging": 69,
    "loading": 149,
    "qcDetails": {
      "23": "DTQC24"
    }
  },
  {
    "time": 3430.29,
    "pipeline": "Wharf",
    "activity": "Berthing",
    "eventName": "OnStart",
    "vesselId": "V0006",
    "wharf": "wharf_N",
    "wharfmark_start": 432.61,
    "wharfmark_end": 853.21,
    "LOA": 390.61,
    "discharging": 2442,
    "loading": 689,
    "qcDetails": {
      "25": "DTQC26",
      "26": "DTQC27",
      "27": "DTQC28",
      "28": "DTQC29"
    }
  },
  {
    "time": 3563.41,
    "pipeline": "Wharf",
    "activity": "Berthing",
    "eventName": "OnStart",
    "vesselId": "V0004",
    "wharf": "wharf_S",
    "wharfmark_start": 347.23,
    "wharfmark_end": 707.63,
    "LOA": 330.36,
    "discharging": 1659,
    "loading": 1801,
    "qcDetails": {
      "6": "DTQC47",
      "7": "DTQC48",
      "8": "DTQC49",
      "9": "DTQC50"
    }
  },
  {
    "time": 4072.58,
    "pipeline": "Wharf",
    "activity": "Berthing",
    "eventName": "OnStart",
    "vesselId": "V0017",
    "wharf": "wharf_N",
    "wharfmark_start": 2988.58,
    "wharfmark_end": 3263.08,
    "LOA": 244.51,
    "discharging": 1481,
    "loading": 885,
    "qcDetails": {
      "1": "DTQC02",
      "2": "DTQC03",
      "3": "DTQC04",
      "4": "DTQC05"
    }
  },
  {
    "time": 4621.43,
    "pipeline": "Wharf",
    "activity": "Berthing",
    "eventName": "OnStart",
    "vesselId": "V0008",
    "wharf": "wharf_S",
    "wharfmark_start": 757.07,
    "wharfmark_end": 1034.67,
    "LOA": 247.64,
    "discharging": 1012,
    "loading": 361,
    "qcDetails": {
      "15": "DTQC56",
      "16": "DTQC57",
      "17": "DTQC58",
      "18": "DTQC59"
    }
  },
  {
    "time": 4816.78,
    "pipeline": "Wharf",
    "activity": "Berthing",
    "eventName": "OnStart",
    "vesselId": "V0035",
    "wharf": "wharf_N",
    "wharfmark_start": 2685.81,
    "wharfmark_end": 2950.01,
    "LOA": 234.22,
    "discharging": 6545,
    "loading": 1982,
    "qcDetails": {
      "9": "DTQC10",
      "10": "DTQC11"
    }
  },
  {
    "time": 4917.02,
    "pipeline": "Wharf",
    "activity": "Berthing",
    "eventName": "OnStart",
    "vesselId": "V0009",
    "wharf": "wharf_S",
    "wharfmark_start": 3294.66,
    "wharfmark_end": 3496.46,
    "LOA": 171.76,
    "discharging": 910,
    "loading": 487,
    "qcDetails": {
      "12": "DTQC53",
      "13": "DTQC54"
    }
  },
  {
    "time": 5187.08,
    "pipeline": "Wharf",
    "activity": "Berthing",
    "eventName": "OnStart",
    "vesselId": "V0007",
    "wharf": "wharf_N",
    "wharfmark_start": 893.68,
    "wharfmark_end": 1200.08,
    "LOA": 276.38,
    "discharging": 1301,
    "loading": 646,
    "qcDetails": {
      "17": "DTQC18",
      "18": "DTQC19",
      "19": "DTQC20",
      "20": "DTQC21"
    }
  },
  {
    "time": 5387.91,
    "pipeline": "Wharf",
    "activity": "Berthing",
    "eventName": "OnStart",
    "vesselId": "V0011",
    "wharf": "wharf_S",
    "wharfmark_start": 1070.14,
    "wharfmark_end": 1463.34,
    "LOA": 363.23,
    "discharging": 1779,
    "loading": 628,
    "qcDetails": {
      "16": "DTQC57",
      "17": "DTQC58",
      "18": "DTQC59",
      "19": "DTQC60"
    }
  },
  {
    "time": 6085.09,
    "pipeline": "Wharf",
    "activity": "Berthing",
    "eventName": "OnStart",
    "vesselId": "V0010",
    "wharf": "wharf_N",
    "wharfmark_start": 1235.22,
    "wharfmark_end": 1578.52,
    "LOA": 313.28,
    "discharging": 3983,
    "loading": 925,
    "qcDetails": {
      "24": "DTQC25",
      "25": "DTQC26",
      "26": "DTQC27"
    }
  },
  {
    "time": 6460.4,
    "pipeline": "Wharf",
    "activity": "Berthing",
    "eventName": "OnStart",
    "vesselId": "V0019",
    "wharf": "wharf_S",
    "wharfmark_start": 2957.8,
    "wharfmark_end": 3251.7,
    "LOA": 263.91,
    "discharging": 1320,
    "loading": 1724,
    "qcDetails": {
      "6": "DTQC47",
      "7": "DTQC48",
      "8": "DTQC49"
    }
  },
  {
    "time": 6571.49,
    "pipeline": "Wharf",
    "activity": "Berthing",
    "eventName": "OnStart",
    "vesselId": "V0014",
    "wharf": "wharf_S",
    "wharfmark_start": 1508.88,
    "wharfmark_end": 1889.18,
    "LOA": 350.29,
    "discharging": 616,
    "loading": 695,
    "qcDetails": {
      "23": "DTQC64",
      "24": "DTQC65",
      "25": "DTQC66",
      "26": "DTQC67"
    }
  },
  {
    "time": 6777.21,
    "pipeline": "Wharf",
    "activity": "Berthing",
    "eventName": "OnReadyToDepart",
    "vesselId": "V0012"
  },
  {
    "time": 7544.45,
    "pipeline": "Wharf",
    "activity": "Berthing",
    "eventName": "OnStart",
    "vesselId": "V0016",
    "wharf": "wharf_S",
    "wharfmark_start": 1923.98,
    "wharfmark_end": 2320.88,
    "LOA": 366.94,
    "discharging": 972,
    "loading": 656,
    "qcDetails": {
      "32": "DTQC73",
      "33": "DTQC74",
      "34": "DTQC75"
    }
  },
  {
    "time": 7550.9,
    "pipeline": "Wharf",
    "activity": "Berthing",
    "eventName": "OnStart",
    "vesselId": "V0013",
    "wharf": "wharf_N",
    "wharfmark_start": 1624.06,
    "wharfmark_end": 1885.96,
    "LOA": 231.96,
    "discharging": 594,
    "loading": 349,
    "qcDetails": {
      "18": "DTQC19"
    }
  },
  {
    "time": 7684.8,
    "pipeline": "Wharf",
    "activity": "Berthing",
    "eventName": "OnReadyToDepart",
    "vesselId": "V0005"
  },
  {
    "time": 8623.21,
    "pipeline": "Wharf",
    "activity": "Berthing",
    "eventName": "OnStart",
    "vesselId": "V0021",
    "wharf": "wharf_S",
    "wharfmark_start": 2362.28,
    "wharfmark_end": 2663.28,
    "LOA": 271,
    "discharging": 581,
    "loading": 261,
    "qcDetails": {
      "27": "DTQC68",
      "28": "DTQC69",
      "29": "DTQC70"
    }
  },
  {
    "time": 8664.22,
    "pipeline": "Wharf",
    "activity": "Berthing",
    "eventName": "OnStart",
    "vesselId": "V0015",
    "wharf": "wharf_N",
    "wharfmark_start": 1925.8,
    "wharfmark_end": 2151.6,
    "LOA": 195.76,
    "discharging": 753,
    "loading": 472,
    "qcDetails": {
      "3": "DTQC04",
      "4": "DTQC05",
      "5": "DTQC06",
      "6": "DTQC07"
    }
  },
  {
    "time": 9249.74,
    "pipeline": "Wharf",
    "activity": "Berthing",
    "eventName": "OnStart",
    "vesselId": "V0026",
    "wharf": "wharf_S",
    "wharfmark_start": 2761.66,
    "wharfmark_end": 2912.22,
    "LOA": 118.48,
    "discharging": 102,
    "loading": 649,
    "qcDetails": {
      "10": "DTQC51",
      "11": "DTQC52",
      "12": "DTQC53"
    }
  },
  {
    "time": 9440.1,
    "pipeline": "Wharf",
    "activity": "Berthing",
    "eventName": "OnReadyToDepart",
    "vesselId": "V0008"
  },
  {
    "time": 9469.33,
    "pipeline": "Wharf",
    "activity": "Berthing",
    "eventName": "OnStart",
    "vesselId": "V0022",
    "wharf": "wharf_N",
    "wharfmark_start": 3513.14,
    "wharfmark_end": 3735.54,
    "LOA": 192.38,
    "discharging": 550,
    "loading": 730,
    "qcDetails": {
      "2": "DTQC03",
      "3": "DTQC04"
    }
  },
  {
    "time": 9926.1,
    "pipeline": "Wharf",
    "activity": "Berthing",
    "eventName": "OnStart",
    "vesselId": "V0018",
    "wharf": "wharf_N",
    "wharfmark_start": 2191.52,
    "wharfmark_end": 2342.08,
    "LOA": 113.5,
    "discharging": 65,
    "loading": 31,
    "qcDetails": {
      "0": "DTQC01"
    }
  },
  {
    "time": 10846.2,
    "pipeline": "Wharf",
    "activity": "Berthing",
    "eventName": "OnStart",
    "vesselId": "V0023",
    "wharf": "wharf_N",
    "wharfmark_start": 2402.13,
    "wharfmark_end": 2596.73,
    "LOA": 164.61,
    "discharging": 921,
    "loading": 2450,
    "qcDetails": {
      "28": "DTQC29",
      "29": "DTQC30",
      "30": "DTQC31"
    }
  },
  {
    "time": 10974.43,
    "pipeline": "Wharf",
    "activity": "Berthing",
    "eventName": "OnStart",
    "vesselId": "V0024",
    "wharf": "wharf_S",
    "wharfmark_start": 745.68,
    "wharfmark_end": 1039.78,
    "LOA": 264.07,
    "discharging": 1358,
    "loading": 1976,
    "qcDetails": {
      "20": "DTQC61",
      "21": "DTQC62",
      "22": "DTQC63",
      "23": "DTQC64"
    }
  },
  {
    "time": 10984.21,
    "pipeline": "Wharf",
    "activity": "Berthing",
    "eventName": "OnReadyToDepart",
    "vesselId": "V0003"
  },
  {
    "time": 11315.1,
    "pipeline": "Wharf",
    "activity": "Berthing",
    "eventName": "OnReadyToDepart",
    "vesselId": "V0002"
  },
  {
    "time": 11695.11,
    "pipeline": "Wharf",
    "activity": "Berthing",
    "eventName": "OnReadyToDepart",
    "vesselId": "V0014"
  },
  {
    "time": 12169.46,
    "pipeline": "Wharf",
    "activity": "Berthing",
    "eventName": "OnReadyToDepart",
    "vesselId": "V0007"
  },
  {
    "time": 12693.74,
    "pipeline": "Wharf",
    "activity": "Berthing",
    "eventName": "OnReadyToDepart",
    "vesselId": "V0021"
  },
  {
    "time": 12705.78,
    "pipeline": "Wharf",
    "activity": "Berthing",
    "eventName": "OnReadyToDepart",
    "vesselId": "V0018"
  },
  {
    "time": 12764.92,
    "pipeline": "Wharf",
    "activity": "Berthing",
    "eventName": "OnReadyToDepart",
    "vesselId": "V0017"
  },
  {
    "time": 13098.45,
    "pipeline": "Wharf",
    "activity": "Berthing",
    "eventName": "OnStart",
    "vesselId": "V0038",
    "wharf": "wharf_S",
    "wharfmark_start": 1737.86,
    "wharfmark_end": 1888.42,
    "LOA": 117.68,
    "discharging": 439,
    "loading": 326,
    "qcDetails": {
      "26": "DTQC67"
    }
  },
  {
    "time": 13228.81,
    "pipeline": "Wharf",
    "activity": "Berthing",
    "eventName": "OnReadyToDepart",
    "vesselId": "V0015"
  },
  {
    "time": 13237.6,
    "pipeline": "Wharf",
    "activity": "Berthing",
    "eventName": "OnStart",
    "vesselId": "V0037",
    "wharf": "wharf_S",
    "wharfmark_start": 1514.14,
    "wharfmark_end": 1664.7,
    "LOA": 66.52,
    "discharging": 85,
    "loading": 215,
    "qcDetails": {
      "14": "DTQC55"
    }
  },
  {
    "time": 13519.25,
    "pipeline": "Wharf",
    "activity": "Berthing",
    "eventName": "OnReadyToDepart",
    "vesselId": "V0026"
  },
  {
    "time": 14007.65,
    "pipeline": "Wharf",
    "activity": "Berthing",
    "eventName": "OnStart",
    "vesselId": "V0029",
    "wharf": "wharf_S",
    "wharfmark_start": 39.85,
    "wharfmark_end": 193.35,
    "LOA": 123.54,
    "discharging": 197,
    "loading": 1795,
    "qcDetails": {
      "19": "DTQC60",
      "20": "DTQC61"
    }
  },
  {
    "time": 14124.57,
    "pipeline": "Wharf",
    "activity": "Berthing",
    "eventName": "OnReadyToDepart",
    "vesselId": "V0006"
  },
  {
    "time": 14182.02,
    "pipeline": "Wharf",
    "activity": "Berthing",
    "eventName": "OnStart",
    "vesselId": "V0025",
    "wharf": "wharf_N",
    "wharfmark_start": 3125.3,
    "wharfmark_end": 3468.0,
    "LOA": 312.66,
    "discharging": 987,
    "loading": 1210,
    "qcDetails": {
      "4": "DTQC05",
      "5": "DTQC06",
      "6": "DTQC07",
      "7": "DTQC08"
    }
  },
  {
    "time": 14190.42,
    "pipeline": "Wharf",
    "activity": "Berthing",
    "eventName": "OnStart",
    "vesselId": "V0036",
    "wharf": "wharf_N",
    "wharfmark_start": 899.38,
    "wharfmark_end": 1100.08,
    "LOA": 170.66,
    "discharging": 618,
    "loading": 2107,
    "qcDetails": {
      "3": "DTQC04",
      "4": "DTQC05",
      "5": "DTQC06"
    }
  },
  {
    "time": 14211.09,
    "pipeline": "Wharf",
    "activity": "Berthing",
    "eventName": "OnReadyToDepart",
    "vesselId": "V0011"
  },
  {
    "time": 14296.18,
    "pipeline": "Wharf",
    "activity": "Berthing",
    "eventName": "OnStart",
    "vesselId": "V0033",
    "wharf": "wharf_S",
    "wharfmark_start": 2402.74,
    "wharfmark_end": 2670.64,
    "LOA": 237.94,
    "discharging": 747,
    "loading": 1744,
    "qcDetails": {
      "3": "DTQC44",
      "4": "DTQC45"
    }
  },
  {
    "time": 14740.98,
    "pipeline": "Wharf",
    "activity": "Berthing",
    "eventName": "OnReadyToDepart",
    "vesselId": "V0009"
  },
  {
    "time": 14856.99,
    "pipeline": "Wharf",
    "activity": "Berthing",
    "eventName": "OnStart",
    "vesselId": "V0020",
    "wharf": "wharf_N",
    "wharfmark_start": 1941.06,
    "wharfmark_end": 2358.26,
    "LOA": 387.19,
    "discharging": 1246,
    "loading": 1080,
    "qcDetails": {
      "13": "DTQC14",
      "14": "DTQC15",
      "15": "DTQC16",
      "16": "DTQC17"
    }
  },
  {
    "time": 15009.47,
    "pipeline": "Wharf",
    "activity": "Berthing",
    "eventName": "OnStart",
    "vesselId": "V0030",
    "wharf": "wharf_S",
    "wharfmark_start": 2716.17,
    "wharfmark_end": 2913.67,
    "LOA": 167.51,
    "discharging": 575,
    "loading": 889,
    "qcDetails": {
      "33": "DTQC74",
      "34": "DTQC75"
    }
  },
  {
    "time": 15177.12,
    "pipeline": "Wharf",
    "activity": "Berthing",
    "eventName": "OnReadyToDepart",
    "vesselId": "V0001"
  },
  {
    "time": 15351.45,
    "pipeline": "Wharf",
    "activity": "Berthing",
    "eventName": "OnReadyToDepart",
    "vesselId": "V0016"
  },
  {
    "time": 16038.11,
    "pipeline": "Wharf",
    "activity": "Berthing",
    "eventName": "OnStart",
    "vesselId": "V0042",
    "wharf": "wharf_N",
    "wharfmark_start": 652.51,
    "wharfmark_end": 849.51,
    "LOA": 166.97,
    "discharging": 774,
    "loading": 673,
    "qcDetails": {
      "1": "DTQC02",
      "2": "DTQC03",
      "3": "DTQC04"
    }
  },
  {
    "time": 16056.59,
    "pipeline": "Wharf",
    "activity": "Berthing",
    "eventName": "OnReadyToDepart",
    "vesselId": "V0004"
  },
  {
    "time": 16122.86,
    "pipeline": "Wharf",
    "activity": "Berthing",
    "eventName": "OnStart",
    "vesselId": "V0034",
    "wharf": "wharf_N",
    "wharfmark_start": 438.3,
    "wharfmark_end": 592.7,
    "LOA": 124.36,
    "discharging": 223,
    "loading": 516,
    "qcDetails": {
      "0": "DTQC01",
      "1": "DTQC02"
    }
  },
  {
    "time": 16856.39,
    "pipeline": "Wharf",
    "activity": "Berthing",
    "eventName": "OnStart",
    "vesselId": "V0041",
    "wharf": "wharf_S",
    "wharfmark_start": 2039.31,
    "wharfmark_end": 2358.01,
    "LOA": 288.71,
    "discharging": 7576,
    "loading": 2133,
    "qcDetails": {
      "6": "DTQC47",
      "7": "DTQC48"
    }
  },
  {
    "time": 17374.74,
    "pipeline": "Wharf",
    "activity": "Berthing",
    "eventName": "OnStart",
    "vesselId": "V0039",
    "wharf": "wharf_S",
    "wharfmark_start": 1092.91,
    "wharfmark_end": 1427.51,
    "LOA": 304.6,
    "discharging": 2144,
    "loading": 1293,
    "qcDetails": {
      "13": "DTQC54",
      "14": "DTQC55",
      "15": "DTQC56",
      "16": "DTQC57"
    }
  },
  {
    "time": 17580.26,
    "pipeline": "Wharf",
    "activity": "Berthing",
    "eventName": "OnReadyToDepart",
    "vesselId": "V0037"
  },
  {
    "time": 17606.69,
    "pipeline": "Wharf",
    "activity": "Berthing",
    "eventName": "OnStart",
    "vesselId": "V0043",
    "wharf": "wharf_S",
    "wharfmark_start": 250.46,
    "wharfmark_end": 524.66,
    "LOA": 244.16,
    "discharging": 679,
    "loading": 5052,
    "qcDetails": {
      "1": "DTQC42",
      "2": "DTQC43",
      "3": "DTQC44",
      "4": "DTQC45"
    }
  },
  {
    "time": 17825.21,
    "pipeline": "Wharf",
    "activity": "Berthing",
    "eventName": "OnStart",
    "vesselId": "V0028",
    "wharf": "wharf_S",
    "wharfmark_start": 3386.13,
    "wharfmark_end": 3741.23,
    "LOA": 325.08,
    "discharging": 1560,
    "loading": 593,
    "qcDetails": {
      "29": "DTQC70",
      "30": "DTQC71",
      "31": "DTQC72",
      "32": "DTQC73"
    }
  },
  {
    "time": 18405.82,
    "pipeline": "Wharf",
    "activity": "Berthing",
    "eventName": "OnReadyToDepart",
    "vesselId": "V0022"
  },
  {
    "time": 18970.24,
    "pipeline": "Wharf",
    "activity": "Berthing",
    "eventName": "OnStart",
    "vesselId": "V0027",
    "wharf": "wharf_N",
    "wharfmark_start": 46.52,
    "wharfmark_end": 371.42,
    "LOA": 294.88,
    "discharging": 1698,
    "loading": 2085,
    "qcDetails": {
      "21": "DTQC22",
      "22": "DTQC23",
      "23": "DTQC24",
      "24": "DTQC25"
    }
  },
  {
    "time": 20433.95,
    "pipeline": "Wharf",
    "activity": "Berthing",
    "eventName": "OnStart",
    "vesselId": "V0031",
    "wharf": "wharf_N",
    "wharfmark_start": 3575.06,
    "wharfmark_end": 3725.62,
    "LOA": 84.55,
    "discharging": 53,
    "loading": 482,
    "qcDetails": {
      "13": "DTQC14"
    }
  },
  {
    "time": 20578.0,
    "pipeline": "Wharf",
    "activity": "Berthing",
    "eventName": "OnReadyToDepart",
    "vesselId": "V0013"
  },
  {
    "time": 21324.0,
    "pipeline": "Wharf",
    "activity": "Berthing",
    "eventName": "OnReadyToDepart",
    "vesselId": "V0019"
  },
  {
    "time": 21543.47,
    "pipeline": "Wharf",
    "activity": "Berthing",
    "eventName": "OnReadyToDepart",
    "vesselId": "V0034"
  },
  {
    "time": 22520.31,
    "pipeline": "Wharf",
    "activity": "Berthing",
    "eventName": "OnReadyToDepart",
    "vesselId": "V0025"
  },
  {
    "time": 22820.93,
    "pipeline": "Wharf",
    "activity": "Berthing",
    "eventName": "OnStart",
    "vesselId": "V0044",
    "wharf": "wharf_S",
    "wharfmark_start": 2990.53,
    "wharfmark_end": 3348.53,
    "LOA": 327.94,
    "discharging": 2375,
    "loading": 903,
    "qcDetails": {
      "27": "DTQC68",
      "28": "DTQC69",
      "29": "DTQC70",
      "30": "DTQC71"
    }
  },
  {
    "time": 23122.14,
    "pipeline": "Wharf",
    "activity": "Berthing",
    "eventName": "OnReadyToDepart",
    "vesselId": "V0042"
  },
  {
    "time": 23346.89,
    "pipeline": "Wharf",
    "activity": "Berthing",
    "eventName": "OnReadyToDepart",
    "vesselId": "V0020"
  },
  {
    "time": 23578.38,
    "pipeline": "Wharf",
    "activity": "Berthing",
    "eventName": "OnReadyToDepart",
    "vesselId": "V0038"
  },
  {
    "time": 23748.24,
    "pipeline": "Wharf",
    "activity": "Berthing",
    "eventName": "OnReadyToDepart",
    "vesselId": "V0024"
  },
  {
    "time": 24591.31,
    "pipeline": "Wharf",
    "activity": "Berthing",
    "eventName": "OnStart",
    "vesselId": "V0032",
    "wharf": "wharf_N",
    "wharfmark_start": 3172.11,
    "wharfmark_end": 3535.21,
    "LOA": 333.02,
    "discharging": 2182,
    "loading": 603,
    "qcDetails": {
      "7": "DTQC08",
      "8": "DTQC09",
      "9": "DTQC10",
      "10": "DTQC11"
    }
  },
  {
    "time": 25875.37,
    "pipeline": "Wharf",
    "activity": "Berthing",
    "eventName": "OnStart",
    "vesselId": "V0040",
    "wharf": "wharf_N",
    "wharfmark_start": 421.23,
    "wharfmark_end": 715.13,
    "LOA": 263.88,
    "discharging": 1640,
    "loading": 495,
    "qcDetails": {
      "22": "DTQC23",
      "23": "DTQC24",
      "24": "DTQC25",
      "25": "DTQC26"
    }
  },
  {
    "time": 25891.51,
    "pipeline": "Wharf",
    "activity": "Berthing",
    "eventName": "OnReadyToDepart",
    "vesselId": "V0028"
  },
  {
    "time": 26476.66,
    "pipeline": "Wharf",
    "activity": "Berthing",
    "eventName": "OnReadyToDepart",
    "vesselId": "V0030"
  },
  {
    "time": 27552.47,
    "pipeline": "Wharf",
    "activity": "Berthing",
    "eventName": "OnReadyToDepart",
    "vesselId": "V0036"
  },
  {
    "time": 28173.86,
    "pipeline": "Wharf",
    "activity": "Berthing",
    "eventName": "OnReadyToDepart",
    "vesselId": "V0010"
  },
  {
    "time": 28471.27,
    "pipeline": "Wharf",
    "activity": "Berthing",
    "eventName": "OnReadyToDepart",
    "vesselId": "V0023"
  },
  {
    "time": 29380.79,
    "pipeline": "Wharf",
    "activity": "Berthing",
    "eventName": "OnReadyToDepart",
    "vesselId": "V0031"
  },
  {
    "time": 29764.9,
    "pipeline": "Wharf",
    "activity": "Berthing",
    "eventName": "OnReadyToDepart",
    "vesselId": "V0039"
  },
  {
    "time": 30174.68,
    "pipeline": "Wharf",
    "activity": "Berthing",
    "eventName": "OnReadyToDepart",
    "vesselId": "V0029"
  },
  {
    "time": 32547.93,
    "pipeline": "Wharf",
    "activity": "Berthing",
    "eventName": "OnReadyToDepart",
    "vesselId": "V0033"
  },
  {
    "time": 32678.93,
    "pipeline": "Wharf",
    "activity": "Berthing",
    "eventName": "OnReadyToDepart",
    "vesselId": "V0035"
  },
  {
    "time": 33520.91,
    "pipeline": "Wharf",
    "activity": "Berthing",
    "eventName": "OnReadyToDepart",
    "vesselId": "V0040"
  },
  {
    "time": 33871.18,
    "pipeline": "Wharf",
    "activity": "Berthing",
    "eventName": "OnReadyToDepart",
    "vesselId": "V0027"
  },
  {
    "time": 34342.7,
    "pipeline": "Wharf",
    "activity": "Berthing",
    "eventName": "OnReadyToDepart",
    "vesselId": "V0032"
  }
]